disturbvalue/__init__.py
disturbvalue/disturbvalue.py
dvreg-1.0.0.0.dist-info/METADATA
dvreg-1.0.0.0.dist-info/WHEEL
dvreg-1.0.0.0.dist-info/top_level.txt
dvreg-1.0.0.0.dist-info/RECORD
