Metadata-Version: 2.1
Name: dvreg
Version: 1.0.0.0
Summary: DisturbValue: a regularization method for regressioin tasks
Home-page: https://sites.google.com/view/yongho-kim/home
Author: Yongho Kim et al.
Author-email: mathkimy@gmail.com
License: MIT
Platform: UNKNOWN
Requires-Python: >=3
